libename/Jeff.py
libename/__init__.py
JeffBrain-0.0.1.dist-info/METADATA
JeffBrain-0.0.1.dist-info/WHEEL
JeffBrain-0.0.1.dist-info/top_level.txt
JeffBrain-0.0.1.dist-info/RECORD
