Metadata-Version: 2.1
Name: JeffBrain
Version: 0.0.1
Summary: Vocal Assisstant
Home-page: UNKNOWN
Author: Gauthegoat (Gauthier Bassereau)
Author-email: <gauthier.bassereau@gmail.com>
License: UNKNOWN
Keywords: python,video,stream,video stream,camera stream,sockets
Platform: UNKNOWN
Classifier: Development Status :: 1 - Planning
Classifier: Intended Audience :: Developers
Classifier: Programming Language :: Python :: 3
Classifier: Operating System :: Unix
Classifier: Operating System :: MacOS :: MacOS X
Classifier: Operating System :: Microsoft :: Windows
Requires-Dist: speech-recognition
Requires-Dist: pyttsx3
Requires-Dist: pywhatkit
Requires-Dist: datetime
Requires-Dist: wikipedia
Requires-Dist: time
Requires-Dist: urllib.request
Requires-Dist: googletrans
Requires-Dist: os
Requires-Dist: webbrowser
Requires-Dist: subprocess
